filter_illumina_index/__init__.py
filter_illumina_index/filter_illumina_index.py
filter_illumina_index/tests/__init__.py
filter_illumina_index/tests/test_filter_illumina_index.py
filter_illumina_index/tests/data/example_reads.fastq
filter_illumina_index/tests/data/example_reads.fastq.gz
filter_illumina_index/tests/data/test_reads_GATCGTGT++TCTATCCT.fastq
filter_illumina_index/tests/data/test_reads_GATCGTGT+TCTATCCT+ATG.fastq
filter_illumina_index/tests/data/test_reads_GATCGTGT+TCTATCCT.fastq
filter_illumina_index/tests/data/test_reads_GATCGTGT.fastq
filter_illumina_index/tests/data/test_reads_GATCGTGT.fastq.gz
filter_illumina_index/tests/data/test_reads_diffbarcodes.fastq
filter_illumina_index/tests/data/test_reads_invalidbarcodes.fastq
filter_illumina_index/tests/data/test_reads_invaliddouble.fastq
filter_illumina_index/tests/data/results/test_reads_GATCGTGT++TCTATCCT_results_GATCGTGT++TCTATCCT_m0.json
filter_illumina_index/tests/data/results/test_reads_GATCGTGT++TCTATCCT_results_GATCGTGT+TCTATCCT_m0.json
filter_illumina_index/tests/data/results/test_reads_GATCGTGT+TCTATCCT+ATG_results_GATCGTGT+TCTATCCT_m0.json
filter_illumina_index/tests/data/results/test_reads_GATCGTGT+TCTATCCT_filtered_GATCGTGT+TCTATCCT_m0.fastq
filter_illumina_index/tests/data/results/test_reads_GATCGTGT+TCTATCCT_filtered_GATCGTGT+TCTATCCT_m1.fastq
filter_illumina_index/tests/data/results/test_reads_GATCGTGT+TCTATCCT_filtered_GATCGTGT+TCTATCCT_m5.fastq
filter_illumina_index/tests/data/results/test_reads_GATCGTGT+TCTATCCT_filtered_GATCGTGT+pass_m0.fastq
filter_illumina_index/tests/data/results/test_reads_GATCGTGT+TCTATCCT_filtered_pass+TCTATCCT_m0.fastq
filter_illumina_index/tests/data/results/test_reads_GATCGTGT+TCTATCCT_results_GATCGTGT+NNNATCCT_m1.json
filter_illumina_index/tests/data/results/test_reads_GATCGTGT+TCTATCCT_results_GATCGTGT+NNNATCCT_m2.json
filter_illumina_index/tests/data/results/test_reads_GATCGTGT+TCTATCCT_results_GATCGTGT+NNNATCCT_m5.json
filter_illumina_index-1.0.5.dist-info/LICENSE
filter_illumina_index-1.0.5.dist-info/METADATA
filter_illumina_index-1.0.5.dist-info/WHEEL
filter_illumina_index-1.0.5.dist-info/entry_points.txt
filter_illumina_index-1.0.5.dist-info/top_level.txt
filter_illumina_index-1.0.5.dist-info/RECORD
