Metadata-Version: 2.1
Name: filter-illumina-index
Version: 1.0.5
Summary: Filter a Illumina FASTQ file based on index sequence
Home-page: https://github.com/twlee79/filter_illumina_index
Author: Tet Woo Lee
Author-email: developer@twlee.nz
Classifier: Programming Language :: Python :: 3
Classifier: License :: OSI Approved :: GNU General Public License v3 (GPLv3)
Classifier: Operating System :: OS Independent
License-File: LICENSE
Requires-Dist: xopen (>=v0.9.0)
Requires-Dist: dnaio (>=v0.4.1)
